README.md
setup.cfg
setup.py
promt_tr/__init__.py
promt_tr/__main__.py
promt_tr/promt_tr.py
promt_tr_free.egg-info/PKG-INFO
promt_tr_free.egg-info/SOURCES.txt
promt_tr_free.egg-info/dependency_links.txt
promt_tr_free.egg-info/requires.txt
promt_tr_free.egg-info/top_level.txt