Metadata-Version: 2.1
Name: promt-tr-free
Version: 0.0.1
Summary: promt translate for free
Home-page: http://github.com/ffreemt/promt-tr-free
Author: mikeee
License: MIT License
Download-URL: https://github.com/ffreemt/promt-tr-free/archive/v_001.tar.gz
Keywords: machine translation,free,scraping
Platform: UNKNOWN
Classifier: Development Status :: 3 - Alpha
Classifier: Intended Audience :: Developers
Classifier: Programming Language :: Python :: 3
Classifier: Programming Language :: Python :: 3.6
Classifier: License :: OSI Approved :: MIT License
